cdstarcat/__init__.py
cdstarcat/__main__.py
cdstarcat/catalog.py
cdstarcat/cli_util.py
cdstarcat/resources.py
cdstarcat/commands/__init__.py
cdstarcat/commands/add.py
cdstarcat/commands/cleanup.py
cdstarcat/commands/create.py
cdstarcat/commands/delete.py
cdstarcat/commands/download.py
cdstarcat/commands/stats.py
cdstarcat/commands/update.py
cdstarcat-1.5.0.dist-info/LICENSE
cdstarcat-1.5.0.dist-info/METADATA
cdstarcat-1.5.0.dist-info/WHEEL
cdstarcat-1.5.0.dist-info/entry_points.txt
cdstarcat-1.5.0.dist-info/top_level.txt
cdstarcat-1.5.0.dist-info/RECORD
